investorzilla/__init__.py
investorzilla/__main__.py
investorzilla/datacache.py
investorzilla/fund.py
investorzilla/investor.py
investorzilla/investorzilla.svg
investorzilla/monetary_time_series.py
investorzilla/portfolio.py
investorzilla/streamlit_ui.py
investorzilla/currency/brasil_banco_central.py
investorzilla/currency/cryptocompare.py
investorzilla/marketindex/alphavantage.py
investorzilla/marketindex/brasil_banco_central.py
investorzilla/marketindex/federal_reserve.py
investorzilla/marketindex/yahoo_finance.py
investorzilla/portfolios/app-credentials-for-google-sheets.json
investorzilla/portfolios/google_sheets.py
investorzilla/portfolios/uri.py
investorzilla-6.3.2.dist-info/licenses/LICENSE
investorzilla-6.3.2.dist-info/METADATA
investorzilla-6.3.2.dist-info/WHEEL
investorzilla-6.3.2.dist-info/entry_points.txt
investorzilla-6.3.2.dist-info/top_level.txt
investorzilla-6.3.2.dist-info/RECORD
