Metadata-Version: 2.4
Name: investorzilla
Version: 6.3.2
Summary: Manage your investments like a data scientist
Author-email: Avi Alkalay <avi@unix.sh>
License:                     GNU GENERAL PUBLIC LICENSE
Project-URL: Homepage, https://github.com/avibrazil/investorzilla
Project-URL: Source, https://github.com/avibrazil/investorzilla
Project-URL: Issues, https://github.com/avibrazil/investorzilla/issues/new/choose
Project-URL: Pypi, https://pypi.org/project/investorzilla
Keywords: investments
Classifier: Programming Language :: Python :: 3
Classifier: Operating System :: OS Independent
Classifier: License :: OSI Approved :: GNU Library or Lesser General Public License (LGPL)
Classifier: Development Status :: 5 - Production/Stable
Classifier: Environment :: Web Environment
Classifier: Intended Audience :: Financial and Insurance Industry
Classifier: Topic :: Office/Business :: Financial :: Investment
Requires-Python: >=3.9
License-File: LICENSE
Requires-Dist: pandas>=2
Requires-Dist: pandas_datareader
Requires-Dist: google-api-python-client
Requires-Dist: google-auth-httplib2
Requires-Dist: google-auth-oauthlib
Requires-Dist: tzlocal
Requires-Dist: sqlalchemy
Requires-Dist: matplotlib
Requires-Dist: certifi
Requires-Dist: pyaml
Requires-Dist: streamlit[auth]
Requires-Dist: extra_streamlit_components
Provides-Extra: docs
Requires-Dist: streamlit; extra == "docs"
Dynamic: license-file
